{"id":"https://contentapi.theodi.org/open-data-so-what-finding-the-value.json","web_url":"http://theodi.org/courses/open-data-so-what-finding-the-value-in-open-data/2015-03-25","slug":"open-data-so-what-finding-the-value","title":"So What? Finding the Value in Open Data: 25 March, 2015","format":"course_instance","updated_at":"2015-09-11T09:58:42+00:00","created_at":"2015-01-15T16:37:03+00:00","tag_ids":["course","odi-leeds","open-data","introduction","training"],"tags":[{"id":"https://contentapi.theodi.org/tags/keywords/course.json","web_url":null,"title":"course","details":{"type":"keyword"},"content_with_tag":{"id":"https://contentapi.theodi.org/with_tag.json?keyword=course","web_url":"http://theodi.org/tags/course","slug":"course"}},{"id":"https://contentapi.theodi.org/tags/keywords/odi-leeds.json","web_url":null,"title":"ODI Leeds","details":{"type":"keyword"},"content_with_tag":{"id":"https://contentapi.theodi.org/with_tag.json?keyword=odi-leeds","web_url":"http://theodi.org/tags/odi-leeds","slug":"odi-leeds"}},{"id":"https://contentapi.theodi.org/tags/keywords/open-data.json","web_url":null,"title":"open data","details":{"type":"keyword"},"content_with_tag":{"id":"https://contentapi.theodi.org/with_tag.json?keyword=open-data","web_url":"http://theodi.org/tags/open-data","slug":"open-data"}},{"id":"https://contentapi.theodi.org/tags/keywords/introduction.json","web_url":null,"title":"introduction","details":{"type":"keyword"},"content_with_tag":{"id":"https://contentapi.theodi.org/with_tag.json?keyword=introduction","web_url":"http://theodi.org/tags/introduction","slug":"introduction"}},{"id":"https://contentapi.theodi.org/tags/keywords/training.json","web_url":null,"title":"training","details":{"type":"keyword"},"content_with_tag":{"id":"https://contentapi.theodi.org/with_tag.json?keyword=training","web_url":"http://theodi.org/tags/training","slug":"training"}}],"details":{"business_proposition":false,"description":"","excerpt":"","language":"en","need_extended_font":false,"alternative_title":"Leeds Node - Course - Open Data so what? Finding the value in open data ","url":"https://www.eventbrite.co.uk/e/open-data-so-what-finding-the-value-in-open-data-tickets-15030075360?ref=estw","end_date":"2015-03-25T17:30:00+00:00","location":"ODI Leeds, 3rd Floor Munro House, Duke Street, Leeds, West Yorkshire LS9 8AG","course":"open-data-so-what-finding-the-value-in-open-data","date":"2015-03-25T13:30:00+00:00","price":"From £65+VAT","trainers":["","edafe-onerhime"],"organizations":[],"author":{}},"related_external_links":[],"related":[],"organizations":[],"author":{}}