{"id":"https://contentapi.theodi.org/dubai.json","web_url":"http://theodi.org/nodes/dubai","slug":"dubai","title":"Dubai","format":"node","updated_at":"2016-01-05T11:52:11+00:00","created_at":"2013-10-28T15:32:09+00:00","tag_ids":["node","dubai"],"tags":[{"id":"https://contentapi.theodi.org/tags/keywords/node.json","web_url":null,"title":"Node","details":{"type":"keyword"},"content_with_tag":{"id":"https://contentapi.theodi.org/with_tag.json?keyword=node","web_url":"http://theodi.org/tags/node","slug":"node"}},{"id":"https://contentapi.theodi.org/tags/keywords/dubai.json","web_url":null,"title":"Dubai","details":{"type":"keyword"},"content_with_tag":{"id":"https://contentapi.theodi.org/with_tag.json?keyword=dubai","web_url":"http://theodi.org/tags/dubai","slug":"dubai"}}],"details":{"need_id":"","business_proposition":false,"description":"<p><strong>Learning & Network node</strong></p>\n<p>Exantium is a leading UAE-based advisory firm focusing on the public sector transformation in the GCC and the Arab world, driven by cutting-edge innovations, strategic digital transformation initiatives and world-class informational policies.</p>\n<p><b>To learn more about ODI Dubai visit their <a href=\"http://dubai.theodi.org/\">website</a></b>.</p>","excerpt":"Learning & Network node\r","language":"en","need_extended_font":false,"alternative_title":"","url":"http://exantium.com/","telephone":"","twitter":"","linkedin":"","email":"ibrahim@exantium.com","location":[25.09781,55.1563],"level":"city","region":"AE","beta":false,"join_date":"2013-10-29T00:00:00+00:00","area":"Dubai","host":"Exantium","organizations":[],"author":{},"logo":{}},"related_external_links":[],"related":[],"organizations":[],"author":{}}