{"id":"https://contentapi.theodi.org/odi-futures-how-to-scale-open-smart-cities-data-networks-culture.json","web_url":"http://theodi.org/workshops/odi-futures-how-to-scale-open-smart-cities-data-networks-culture","slug":"odi-futures-how-to-scale-open-smart-cities-data-networks-culture","title":"ODI Futures: How to scale open smart cities: data, networks, culture","format":"event","updated_at":"2015-09-11T10:00:08+00:00","created_at":"2015-04-07T12:47:04+00:00","tag_ids":["event","smart-cities","open-data","event:workshop"],"tags":[{"id":"https://contentapi.theodi.org/tags/keywords/event.json","web_url":null,"title":"event","details":{"type":"keyword"},"content_with_tag":{"id":"https://contentapi.theodi.org/with_tag.json?keyword=event","web_url":"http://theodi.org/tags/event","slug":"event"}},{"id":"https://contentapi.theodi.org/tags/keywords/smart-cities.json","web_url":null,"title":"Smart cities","details":{"type":"keyword"},"content_with_tag":{"id":"https://contentapi.theodi.org/with_tag.json?keyword=smart-cities","web_url":"http://theodi.org/tags/smart-cities","slug":"smart-cities"}},{"id":"https://contentapi.theodi.org/tags/keywords/open-data.json","web_url":null,"title":"open data","details":{"type":"keyword"},"content_with_tag":{"id":"https://contentapi.theodi.org/with_tag.json?keyword=open-data","web_url":"http://theodi.org/tags/open-data","slug":"open-data"}},{"id":"https://contentapi.theodi.org/tags/events/event%3Aworkshop.json","web_url":null,"title":"Workshops","details":{"description":"Workshop","type":"event"},"content_with_tag":{"id":"https://contentapi.theodi.org/with_tag.json?event=event%3Aworkshop","web_url":"http://theodi.org/tags/event%3Aworkshop","slug":"event:workshop"}}],"details":{"business_proposition":false,"description":"<p>The ODI and Arup are hosting a smart cities event on 20 April which takes a forward-look at the 'open smart city'.</p>\n<p>ODI Future events aim to bring business and academia together to examine the potential for open data and how it might impact the future. They intend to be thought provoking and create a real discussion with those who attend. Each event is recorded and we publish audio and slides for each session.</p>\n<p>There will be over 100 attendees from the SmartLondon board, Arup, ODI Members, ODI start ups, Smart Cities APPG members as well as others in the smart cities and open data communities.</p>\n<p><strong><a href=\"http://www.eventbrite.co.uk/e/odi-futures-how-to-scale-open-smart-cities-data-networks-culture-tickets-15554497922\">Book your place here</a></strong></p>\n<p><strong>Topics for discussion include:</strong></p>\n<ul>\n<li>How can open and ‘smart’ scale to impact all key aspects of a city? </li>\n<li>What are the principles and key ingredients (social, cultural, technical) that will make this happen?</li>\n<li>What is the role of open data and open culture?</li>\n<li>What visions already exist to show how this can be realised</li>\n<li>Where are the gaps? What else is needed?</li>\n<li>What are the challenges?</li>\n</ul>\n<p><strong>09:00 Registration, tea and coffee</strong></p>\n<p><strong>09:30 - 11:00 Session 1</strong></p>\n<ul>\n<li>Dr. Tom Heath, Head of Research, Open Data Institute</li>\n<li>Rick Robinson, Smart Data &amp; Technology Director, Amey</li>\n<li>Emer Coleman, Director of Business Development, TransportAPI</li>\n<li>Dan Hill, Executive Director of Futures and Best Practice, Future Cities Catapult</li>\n<li>Simon Gough, Director, Redfront, ODI Devon</li>\n</ul>\n<p>Q&amp;A discussion with all speakers</p>\n<p><strong>11:00 Break</strong></p>\n<p><strong>11:30 - 13:00 Session 2</strong></p>\n<ul>\n<li>Volker Buscher, Director IT &amp; Comms Practice; Smart Cities Leader, Arup</li>\n<li>Yodit Stanton, Founder &amp; CEO, Opensensors.IO</li>\n<li>Gavin Chait, Lead Consultant, Whythawk</li>\n<li>Kevin O'Malley, Partnership Development Manager, City Innovation, Bristol City Council</li>\n</ul>\n<p>Q&amp;A discussion with all speakers</p>\n<p><strong>13:00 Lunch is included for all attendees</strong></p>\n<p><strong>14:00 - 17:00 Optional Workshop</strong></p>\n<p><strong>Building the smart city: An IoT workshop with OpenSensors</strong></p>\n<p>And if that's not enough for one day... join OpenSensors after lunch for a practical introduction to the systems, technologies and opportunities of the smarter city. To attend this second event you must register your place separately <a href=\"https://www.eventbrite.co.uk/e/building-the-smart-city-an-iot-workshop-tickets-16034838634\">here</a>.</p>\n<p><strong>Twitter: @ODIHQ #ODIFutures</strong></p>\n<iframe src=\"//eventbrite.co.uk/tickets-external?eid=15554497922&amp;ref=etckt\" frameborder=\"0\" height=\"536\" width=\"100%\" ></iframe>","excerpt":"The ODI and Arup are hosting a smart cities event on 20 April which takes a forward-look at the 'open smart city'.\r","language":"en","need_extended_font":false,"alternative_title":"ODI Futures: How to scale open smart cities: data, networks, culture","end_date":"2015-04-20T12:00:00+00:00","location":"Arup, 8 Fitzroy Street, London, W1T 4BQ","start_date":"2015-04-20T08:00:00+00:00","booking_url":"http://www.eventbrite.co.uk/e/odi-futures-how-to-scale-open-smart-cities-data-networks-culture-tickets-15554497922","hashtag":"","event_type":"event:workshop","organizations":[],"author":{"name":"Open Data Institute","slug":"odi","state":"published","web_url":"http://theodi.org/odi","tag_ids":[]}},"related_external_links":[],"related":[{"id":"https://contentapi.theodi.org/show-me-the-future-of-food-and-open-data.json","web_url":"http://theodi.org/research-afternoons/show-me-the-future-of-food-and-open-data","slug":"show-me-the-future-of-food-and-open-data","title":"Show me the future of.... food and open data","format":"event","updated_at":"2015-09-11T09:53:13+00:00","created_at":"2013-10-24T11:55:53+00:00","tag_ids":["featured","event:research-afternoon"],"extras":{"start_date":"2013-11-28T14:00:00+00:00","end_date":"2013-11-28T17:00:00+00:00","location":"Open Data Institute, 65 Clifton Street, London, EC2A 4JE "}},{"id":"https://contentapi.theodi.org/show-me-the-future-of-the-built-environment-and-open-data.json","web_url":"http://theodi.org/research-afternoons/show-me-the-future-of-the-built-environment-and-open-data","slug":"show-me-the-future-of-the-built-environment-and-open-data","title":"Show me the future of: the built environment and open data","format":"event","updated_at":"2015-09-11T09:55:37+00:00","created_at":"2014-04-08T14:12:01+00:00","tag_ids":["event:research-afternoon"],"extras":{"start_date":"2014-05-19T13:00:00+00:00","end_date":"2014-05-19T16:00:00+00:00","location":"Highfield House (Room A1), The University of Nottingham, University Park, Nottingham, NG7 2RD"}},{"id":"https://contentapi.theodi.org/latin-america-paves-the-way-for-smart-cities-and-open-data-startups.json","web_url":"http://theodi.org/blog/latin-america-paves-the-way-for-smart-cities-and-open-data-startups","slug":"latin-america-paves-the-way-for-smart-cities-and-open-data-startups","title":"Latin America paves the way for smart cities and open data startups","format":"article","updated_at":"2015-09-11T09:57:26+00:00","created_at":"2014-10-20T14:01:22+00:00","tag_ids":["blog","mexico","smart-cities","training"]},{"id":"https://contentapi.theodi.org/odi-startups-who-they-are-and-what-they-do-in-60-seconds.json","web_url":"http://theodi.org/blog/odi-startups-who-they-are-and-what-they-do-in-60-seconds","slug":"odi-startups-who-they-are-and-what-they-do-in-60-seconds","title":"ODI startups: Who they are and what they do (in 60 seconds)","format":"article","updated_at":"2015-09-11T09:56:31+00:00","created_at":"2014-07-24T15:17:47+00:00","tag_ids":["blog"]}],"organizations":[],"author":{"name":"Open Data Institute","slug":"odi","state":"published","web_url":"http://theodi.org/odi","tag_ids":[]}}